zlang/__init__.py
zlang/__main__.py
zlang/logger.py
zlang/translators/__init__.py
zlang/translators/_c.py
zlang/translators/_lua.py
zlang/translators/_py.py
zlang/translators/_zink.py
zlang/translators/t.py
zlang/zink.py
zlang-2.8.6.dist-info/METADATA
zlang-2.8.6.dist-info/WHEEL
zlang-2.8.6.dist-info/entry_points.txt
zlang-2.8.6.dist-info/licenses/LICENSE.md
zlang-2.8.6.dist-info/RECORD
