Metadata-Version: 2.4
Name: zlang
Version: 2.8.6
Summary: Lightweight and expressive programming language similar to Python
License-File: LICENSE.md
Author: magnesium
Author-email: datas3gment@gmail.com
Requires-Python: >=3.12
Classifier: Programming Language :: Python :: 3
Classifier: Programming Language :: Python :: 3.12
Classifier: Programming Language :: Python :: 3.13
Classifier: Programming Language :: Python :: 3.14
Requires-Dist: argparse (>=1.4.0,<2.0.0)
Requires-Dist: colorama (>=0.4.6,<0.5.0)
Requires-Dist: sly (>=0.5,<0.6)
